eotransform/__init__.py
eotransform/_version.py
eotransform/apply.py
eotransform/collection_transformation.py
eotransform/result.py
eotransform/streamed_process.py
eotransform/protocol/__init__.py
eotransform/protocol/sink.py
eotransform/protocol/stream.py
eotransform/protocol/transformer.py
eotransform/sinks/__init__.py
eotransform/sinks/filtered.py
eotransform/sinks/result.py
eotransform/sinks/sink_to_progress_report.py
eotransform/sinks/with_performance_clock.py
eotransform/transformers/__init__.py
eotransform/transformers/apply_to_enumeration.py
eotransform/transformers/chain.py
eotransform/transformers/compose.py
eotransform/transformers/identity.py
eotransform/transformers/map.py
eotransform/transformers/repeat.py
eotransform/transformers/result.py
eotransform/transformers/send_to_stream.py
eotransform/transformers/to_tuple.py
eotransform/transformers/with_performance_clock.py
eotransform/utilities/__init__.py
eotransform/utilities/profiling.py
eotransform-1.8.0.dist-info/LICENSE
eotransform-1.8.0.dist-info/METADATA
eotransform-1.8.0.dist-info/WHEEL
eotransform-1.8.0.dist-info/top_level.txt
eotransform-1.8.0.dist-info/RECORD
